dsproject/__init__.py
dsproject/config.py
dsproject/dataloader.py
dsproject/eda.py
dsproject/model.py
dsproject/utils.py
dsproject-0.1.0.dist-info/LICENSE
dsproject-0.1.0.dist-info/METADATA
dsproject-0.1.0.dist-info/WHEEL
dsproject-0.1.0.dist-info/entry_points.txt
dsproject-0.1.0.dist-info/top_level.txt
dsproject-0.1.0.dist-info/RECORD
